{
  "db_name": "PostgreSQL",
  "query": "\n            UPDATE users\n            SET is_active = true, updated_at = NOW()\n            WHERE external_id = $1 AND auth_provider = $2\n            RETURNING\n                id, username, email, password_hash, display_name,\n                auth_provider as \"auth_provider: AuthProvider\",\n                external_id, is_admin, is_active, is_service_account, must_change_password,\n                totp_secret, totp_enabled, totp_backup_codes, totp_verified_at,\n                failed_login_attempts, locked_until, last_failed_login_at,\n                password_changed_at, last_login_at, created_at, updated_at\n            ",
  "describe": {
    "columns": [
      {
        "ordinal": 0,
        "name": "id",
        "type_info": "Uuid"
      },
      {
        "ordinal": 1,
        "name": "username",
        "type_info": "Varchar"
      },
      {
        "ordinal": 2,
        "name": "email",
        "type_info": "Varchar"
      },
      {
        "ordinal": 3,
        "name": "password_hash",
        "type_info": "Varchar"
      },
      {
        "ordinal": 4,
        "name": "display_name",
        "type_info": "Varchar"
      },
      {
        "ordinal": 5,
        "name": "auth_provider: AuthProvider",
        "type_info": {
          "Custom": {
            "name": "auth_provider",
            "kind": {
              "Enum": [
                "local",
                "ldap",
                "saml",
                "oidc",
                "ci"
              ]
            }
          }
        }
      },
      {
        "ordinal": 6,
        "name": "external_id",
        "type_info": "Varchar"
      },
      {
        "ordinal": 7,
        "name": "is_admin",
        "type_info": "Bool"
      },
      {
        "ordinal": 8,
        "name": "is_active",
        "type_info": "Bool"
      },
      {
        "ordinal": 9,
        "name": "is_service_account",
        "type_info": "Bool"
      },
      {
        "ordinal": 10,
        "name": "must_change_password",
        "type_info": "Bool"
      },
      {
        "ordinal": 11,
        "name": "totp_secret",
        "type_info": "Text"
      },
      {
        "ordinal": 12,
        "name": "totp_enabled",
        "type_info": "Bool"
      },
      {
        "ordinal": 13,
        "name": "totp_backup_codes",
        "type_info": "Text"
      },
      {
        "ordinal": 14,
        "name": "totp_verified_at",
        "type_info": "Timestamptz"
      },
      {
        "ordinal": 15,
        "name": "failed_login_attempts",
        "type_info": "Int4"
      },
      {
        "ordinal": 16,
        "name": "locked_until",
        "type_info": "Timestamptz"
      },
      {
        "ordinal": 17,
        "name": "last_failed_login_at",
        "type_info": "Timestamptz"
      },
      {
        "ordinal": 18,
        "name": "password_changed_at",
        "type_info": "Timestamptz"
      },
      {
        "ordinal": 19,
        "name": "last_login_at",
        "type_info": "Timestamptz"
      },
      {
        "ordinal": 20,
        "name": "created_at",
        "type_info": "Timestamptz"
      },
      {
        "ordinal": 21,
        "name": "updated_at",
        "type_info": "Timestamptz"
      }
    ],
    "parameters": {
      "Left": [
        "Text",
        {
          "Custom": {
            "name": "auth_provider",
            "kind": {
              "Enum": [
                "local",
                "ldap",
                "saml",
                "oidc",
                "ci"
              ]
            }
          }
        }
      ]
    },
    "nullable": [
      false,
      false,
      false,
      true,
      true,
      false,
      true,
      false,
      false,
      false,
      false,
      true,
      false,
      true,
      true,
      false,
      true,
      true,
      false,
      true,
      false,
      false
    ]
  },
  "hash": "bfba99300202448b3393474afc67a1eeb29f14aa4e4eec264810eff615b15c12"
}
